wry/__init__.py
wry/_version.py
wry/auto_model.py
wry/click_integration.py
wry/comma_separated.py
wry/help_system.py
wry/multi_model.py
wry/py.typed
wry/core/__init__.py
wry/core/accessors.py
wry/core/env_utils.py
wry/core/field_utils.py
wry/core/model.py
wry/core/sources.py
wry-0.6.0.dist-info/licenses/LICENSE
wry-0.6.0.dist-info/METADATA
wry-0.6.0.dist-info/WHEEL
wry-0.6.0.dist-info/top_level.txt
wry-0.6.0.dist-info/RECORD
