Metadata-Version: 2.4
Name: wry
Version: 0.6.0
Summary: Why Repeat Yourself? - Define your CLI once with Pydantic models
Author-email: Tyler House <26489166+tahouse@users.noreply.github.com>
License: MIT
Project-URL: Homepage, https://github.com/tahouse/wry
Project-URL: Documentation, https://github.com/tahouse/wry#readme
Project-URL: Repository, https://github.com/tahouse/wry
Project-URL: Issues, https://github.com/tahouse/wry/issues
Project-URL: Changelog, https://github.com/tahouse/wry/blob/main/CHANGELOG.md
Keywords: cli,pydantic,click,wry,dry,configuration,type-safe
Classifier: Development Status :: 4 - Beta
Classifier: Intended Audience :: Developers
Classifier: License :: OSI Approved :: MIT License
Classifier: Programming Language :: Python :: 3
Classifier: Programming Language :: Python :: 3.10
Classifier: Programming Language :: Python :: 3.11
Classifier: Programming Language :: Python :: 3.12
Classifier: Topic :: Software Development :: Libraries :: Python Modules
Classifier: Topic :: System :: System Shells
Classifier: Topic :: Utilities
Classifier: Typing :: Typed
Requires-Python: >=3.10
License-File: LICENSE
Requires-Dist: click>=8.0
Requires-Dist: pydantic>=2.9.2
Requires-Dist: annotated-types>=0.6.0
Requires-Dist: pydantic-core>=2.23.4
Provides-Extra: dev
Requires-Dist: pytest>=8.4.2; extra == "dev"
Requires-Dist: pytest-cov>=7.0.0; extra == "dev"
Requires-Dist: pytest-xdist>=3.8.0; extra == "dev"
Requires-Dist: coverage[toml]>=7.10.7; extra == "dev"
Requires-Dist: ruff>=0.13.2; extra == "dev"
Requires-Dist: mypy>=1.18.2; extra == "dev"
Requires-Dist: build>=1.2.1; extra == "dev"
Requires-Dist: twine>=6.0.0; extra == "dev"
Requires-Dist: pre-commit>=3.8.0; extra == "dev"
Requires-Dist: safety>=3.2.3; extra == "dev"
Requires-Dist: bandit[toml]>=1.7.5; extra == "dev"
Dynamic: license-file
